<?xml version="1.0" encoding="utf-8"?>
<annotation>
<folder>images</folder>
<filename>bda6d0f8-Screenshot_2023-11-07_at_11-59-32_University_of_New_Haven_Public_Safet_CuZ1zye.png</filename>
<source>
<database>MyDatabase</database>
<annotation>COCO2017</annotation>
<image>flickr</image>
<flickrid>NULL</flickrid>
<annotator>1</annotator>
</source>
<owner>
<flickrid>NULL</flickrid>
<name>Label Studio</name>
</owner>
<size>
<width>877</width>
<height>654</height>
<depth>4</depth>
</size>
<segmented>0</segmented>
<object>
<name>Security</name>
<pose>Unspecified</pose>
<truncated>0</truncated>
<difficult>0</difficult>
<bndbox>
<xmin>498</xmin>
<ymin>205</ymin>
<xmax>650</xmax>
<ymax>435</ymax>
</bndbox>
</object>
<object>
<name>Security</name>
<pose>Unspecified</pose>
<truncated>0</truncated>
<difficult>0</difficult>
<bndbox>
<xmin>262</xmin>
<ymin>289</ymin>
<xmax>271</xmax>
<ymax>300</ymax>
</bndbox>
</object>
<object>
<name>Security</name>
<pose>Unspecified</pose>
<truncated>0</truncated>
<difficult>0</difficult>
<bndbox>
<xmin>192</xmin>
<ymin>204</ymin>
<xmax>269</xmax>
<ymax>387</ymax>
</bndbox>
</object>
<object>
<name>student</name>
<pose>Unspecified</pose>
<truncated>0</truncated>
<difficult>0</difficult>
<bndbox>
<xmin>289</xmin>
<ymin>198</ymin>
<xmax>479</xmax>
<ymax>362</ymax>
</bndbox>
</object>
</annotation>
